<?xml version="1.0" encoding="UTF-8"?>
<objects serializationModel="Studio.02.02.00">
	<object class="AudioFile" id="{e0a298bb-33a7-462e-b285-b4a902d0e451}">
		<property name="assetPath">
			<value>bubble_splash_variant3.wav</value>
		</property>
		<property name="frequencyInKHz">
			<value>44.0999985</value>
		</property>
		<property name="channelCount">
			<value>2</value>
		</property>
		<property name="length">
			<value>3.25</value>
		</property>
		<relationship name="masterAssetFolder">
			<destination>{480f3cd1-1568-4a5b-b558-fa1a2b6f7c48}</destination>
		</relationship>
	</object>
</objects>
